fustor_pusher_openapi/__init__.py
fustor_pusher_openapi-0.2.16.dist-info/METADATA
fustor_pusher_openapi-0.2.16.dist-info/WHEEL
fustor_pusher_openapi-0.2.16.dist-info/entry_points.txt
fustor_pusher_openapi-0.2.16.dist-info/top_level.txt
fustor_pusher_openapi-0.2.16.dist-info/RECORD
