Metadata-Version: 2.4
Name: fustor-pusher-openapi
Version: 0.2.16
Summary: An OpenAPI pusher for Fustor Agent
Author-email: Huajin Wang <wanghuajin999@163.com>
Requires-Python: >=3.11
Requires-Dist: fustor-core
